FIFO Depth/FIFO_Depth.v
module FIFO_Depth(
    input wire clk,
    input wire rst,
    input wire wr_enb,
    input wire rd_enb,
    input wire cs, //chip select
    input wire [data_depth-1:0]data_in,
    output reg [data_depth-1:0]data_out,
    output wire f,
    output wire e
);
parameter data_depth = 32;
parameter fifo_depth = 8;
localparam fifo_depth_log = $clog2(fifo_depth); //To calculate the number of bits needed for addressing FIFO depth
reg [data_depth-1:0] fifo [0:fifo_depth-1]; // 8 locations that can store 32 - bit data
reg [fifo_depth_log:0] wr_ptr;
reg [fifo_depth_log:0] rd_ptr;

// write operation
always @(posedge clk or posedge rst)
begin
    if(rst)
        begin
            wr_ptr <= 0;
        end
    else if(cs && wr_enb && !f)
        begin
            fifo[wr_ptr[fifo_depth_log-1:0]] <= data_in;
            wr_ptr <= wr_ptr + 1'b1;
        end
end

// read operation
always @(posedge clk or posedge rst)
begin
    if(rst)
        begin
            rd_ptr <= 0;
        end
    else if(cs && rd_enb && !e)
        begin
            data_out <= fifo[rd_ptr[fifo_depth_log-1:0]];
            rd_ptr <= rd_ptr + 1'b1;
        end 
end

// full and empty flag generation

    assign e = (rd_ptr == wr_ptr);
    assign f = (rd_ptr == {~wr_ptr[fifo_depth_log], wr_ptr[fifo_depth_log-1:0] });
endmodule

FIFO Depth/FIFO_Depth_tb.v
`timescale 1ns/1ps
module FIFO_Depth_tb;
reg clk;
reg rst;
reg wr_enb;
reg rd_enb;
reg cs;
reg [data_depth-1:0] data_in;
wire [data_depth-1:0] data_out;
wire f;
wire e;

parameter data_depth = 32;
parameter fifo_depth = 8;
integer i;

FIFO_Depth 
    #(.data_depth(data_depth), .fifo_depth(fifo_depth)) 
        dut (
            .clk(clk),
            .rst(rst),
            .wr_enb(wr_enb),
            .rd_enb(rd_enb),
            .cs(cs),
            .data_in(data_in),
            .data_out(data_out),
            .f(f),
            .e(e)
);
initial begin
    $dumpfile("c.vcd");
    $dumpvars(0, FIFO_Depth_tb);
end
always #5 clk = ~clk;

task write_data(input [data_depth-1:0] data);
    begin
        @(posedge clk);
        cs = 1; wr_enb = 1;
        data_in = data;
        $display($time, "write_data data = %0d", data);
        @(posedge clk);
        cs = 1; wr_enb = 0;
    end
endtask

task read_data();
    begin
        @(posedge clk);
        cs = 1; rd_enb = 1;
        @(posedge clk);
        $display($time, "read_data data_out = %0d", data_out);
        cs = 1; rd_enb = 0;
    end
endtask

initial begin
        rst = 1; clk = 0; rd_enb =0; wr_enb = 0; cs = 0;
        @(posedge clk);
        rst = 0;
        $display($time, "\n SCENERIO 1");
        write_data(1);
        write_data(10);
        write_data(100);

        read_data();
        read_data();
        read_data();
        
        $display($time, "\n SCENERIO 2");
        for(i=0; i<fifo_depth; i++)
            begin
                write_data(2**i);
                read_data();
            end
        for(i=0; i<fifo_depth; i++)
            begin
                write_data(3**i);
            end
        for(i=0; i<fifo_depth; i++)
            begin
                read_data();
            end
    #100;
            $finish;
end
endmodule

FIFO Depth/c.vcd
$date
	Fri Jan 16 13:32:44 2026
$end
$version
	Icarus Verilog
$end
$timescale
	1ps
$end
$scope module FIFO_Depth_tb $end
$var wire 1 ! f $end
$var wire 1 " e $end
$var wire 32 # data_out [31:0] $end
$var parameter 32 $ data_depth $end
$var parameter 32 % fifo_depth $end
$var reg 1 & clk $end
$var reg 1 ' cs $end
$var reg 32 ( data_in [31:0] $end
$var reg 1 ) rd_enb $end
$var reg 1 * rst $end
$var reg 1 + wr_enb $end
$var integer 32 , i [31:0] $end
$scope module dut $end
$var wire 1 & clk $end
$var wire 1 ' cs $end
$var wire 32 - data_in [31:0] $end
$var wire 1 ) rd_enb $end
$var wire 1 * rst $end
$var wire 1 + wr_enb $end
$var wire 1 ! f $end
$var wire 1 " e $end
$var parameter 32 . data_depth $end
$var parameter 32 / fifo_depth $end
$var parameter 32 0 fifo_depth_log $end
$var reg 32 1 data_out [31:0] $end
$var reg 4 2 rd_ptr [3:0] $end
$var reg 4 3 wr_ptr [3:0] $end
$upscope $end
$scope task read_data $end
$upscope $end
$scope task write_data $end
$var reg 32 4 data [31:0] $end
$upscope $end
$upscope $end
$enddefinitions $end
$comment Show the parameter values. $end
$dumpall
b11 0
b1000 /
b100000 .
b1000 %
b100000 $
$end
#0
$dumpvars
bx 4
b0 3
b0 2
bx 1
bx -
bx ,
0+
1*
0)
bx (
0'
0&
bx #
1"
0!
$end
#5000
b1 4
0*
1&
#10000
0&
#15000
0"
b1 3
b1 (
b1 -
1+
1'
1&
#20000
0&
#25000
b1010 4
0+
1&
#30000
0&
#35000
b10 3
b1010 (
b1010 -
1+
1&
#40000
0&
#45000
b1100100 4
0+
1&
#50000
0&
#55000
b11 3
b1100100 (
b1100100 -
1+
1&
#60000
0&
#65000
0+
1&
#70000
0&
#75000
b1 2
b1 #
b1 1
1)
1&
#80000
0&
#85000
0)
1&
#90000
0&
#95000
b10 2
b1010 #
b1010 1
1)
1&
#100000
0&
#105000
0)
1&
#110000
0&
#115000
1"
b11 2
b1100100 #
b1100100 1
1)
1&
#120000
0&
#125000
b1 4
b0 ,
0)
1&
#130000
0&
#135000
0"
b100 3
b1 (
b1 -
1+
1&
#140000
0&
#145000
0+
1&
#150000
0&
#155000
1"
b100 2
b1 #
b1 1
1)
1&
#160000
0&
#165000
b10 4
b1 ,
0)
1&
#170000
0&
#175000
0"
b101 3
b10 (
b10 -
1+
1&
#180000
0&
#185000
0+
1&
#190000
0&
#195000
1"
b101 2
b10 #
b10 1
1)
1&
#200000
0&
#205000
b100 4
b10 ,
0)
1&
#210000
0&
#215000
0"
b110 3
b100 (
b100 -
1+
1&
#220000
0&
#225000
0+
1&
#230000
0&
#235000
1"
b110 2
b100 #
b100 1
1)
1&
#240000
0&
#245000
b1000 4
b11 ,
0)
1&
#250000
0&
#255000
0"
b111 3
b1000 (
b1000 -
1+
1&
#260000
0&
#265000
0+
1&
#270000
0&
#275000
1"
b111 2
b1000 #
b1000 1
1)
1&
#280000
0&
#285000
b10000 4
b100 ,
0)
1&
#290000
0&
#295000
0"
b1000 3
b10000 (
b10000 -
1+
1&
#300000
0&
#305000
0+
1&
#310000
0&
#315000
1"
b1000 2
b10000 #
b10000 1
1)
1&
#320000
0&
#325000
b100000 4
b101 ,
0)
1&
#330000
0&
#335000
0"
b1001 3
b100000 (
b100000 -
1+
1&
#340000
0&
#345000
0+
1&
#350000
0&
#355000
1"
b1001 2
b100000 #
b100000 1
1)
1&
#360000
0&
#365000
b1000000 4
b110 ,
0)
1&
#370000
0&
#375000
0"
b1010 3
b1000000 (
b1000000 -
1+
1&
#380000
0&
#385000
0+
1&
#390000
0&
#395000
1"
b1010 2
b1000000 #
b1000000 1
1)
1&
#400000
0&
#405000
b10000000 4
b111 ,
0)
1&
#410000
0&
#415000
0"
b1011 3
b10000000 (
b10000000 -
1+
1&
#420000
0&
#425000
0+
1&
#430000
0&
#435000
1"
b1011 2
b10000000 #
b10000000 1
1)
1&
#440000
0&
#445000
b1 4
b0 ,
0)
1&
#450000
0&
#455000
0"
b1100 3
b1 (
b1 -
1+
1&
#460000
0&
#465000
b11 4
b1 ,
0+
1&
#470000
0&
#475000
b1101 3
b11 (
b11 -
1+
1&
#480000
0&
#485000
b1001 4
b10 ,
0+
1&
#490000
0&
#495000
b1110 3
b1001 (
b1001 -
1+
1&
#500000
0&
#505000
b11011 4
b11 ,
0+
1&
#510000
0&
#515000
b1111 3
b11011 (
b11011 -
1+
1&
#520000
0&
#525000
b1010001 4
b100 ,
0+
1&
#530000
0&
#535000
b0 3
b1010001 (
b1010001 -
1+
1&
#540000
0&
#545000
b11110011 4
b101 ,
0+
1&
#550000
0&
#555000
b1 3
b11110011 (
b11110011 -
1+
1&
#560000
0&
#565000
b1011011001 4
b110 ,
0+
1&
#570000
0&
#575000
b10 3
b1011011001 (
b1011011001 -
1+
1&
#580000
0&
#585000
b100010001011 4
b111 ,
0+
1&
#590000
0&
#595000
1!
b11 3
b100010001011 (
b100010001011 -
1+
1&
#600000
0&
#605000
b0 ,
0+
1&
#610000
0&
#615000
0!
b1100 2
b1 #
b1 1
1)
1&
#620000
0&
#625000
b1 ,
0)
1&
#630000
0&
#635000
b1101 2
b11 #
b11 1
1)
1&
#640000
0&
#645000
b10 ,
0)
1&
#650000
0&
#655000
b1110 2
b1001 #
b1001 1
1)
1&
#660000
0&
#665000
b11 ,
0)
1&
#670000
0&
#675000
b1111 2
b11011 #
b11011 1
1)
1&
#680000
0&
#685000
b100 ,
0)
1&
#690000
0&
#695000
b0 2
b1010001 #
b1010001 1
1)
1&
#700000
0&
#705000
b101 ,
0)
1&
#710000
0&
#715000
b1 2
b11110011 #
b11110011 1
1)
1&
#720000
0&
#725000
b110 ,
0)
1&
#730000
0&
#735000
b10 2
b1011011001 #
b1011011001 1
1)
1&
#740000
0&
#745000
b111 ,
0)
1&
#750000
0&
#755000
1"
b11 2
b100010001011 #
b100010001011 1
1)
1&
#760000
0&
#765000
b1000 ,
0)
1&
